[
  {
    "task1": "T1",
    "duration": 1000
  },
  {
    "name": "Sample Task",
    "duration": 2000
  },
  {
    "name": "Sample Task",
    "duration": 2000
  },
  {
    "name": "Sample Task",
    "duration": 2000
  },
  {
    "name": "Sample Task 2",
    "duration": 2100
  },
  {
    "name": "Sample Task 2012",
    "duration": 2100
  },
  {
    "name": "Sample Task 2019",
    "duration": 1100
  },
  {
    "name": "Sample Task 2012",
    "duration": 2100
  },
  {
    "name": "Sample Task 2042",
    "duration": 2100
  },
  {
    "name": "Sample Task 2042",
    "duration": 2100
  },
  {
    "name": "Sample Task 2042",
    "duration": 2100
  },
  {
    "name": "Sample Task 2042",
    "duration": 2100
  },
  {
    "name": "Sample Task 2042",
    "duration": 2100
  },
  {
    "name": "Sample Task 2042",
    "duration": 2100
  },
  {
    "name": "Sample Task 2042",
    "duration": 2100
  },
  {
    "name": "Sample Task 2042",
    "duration": 2100
  }
]